README.md
setup.py
impresso_commons/__init__.py
impresso_commons/classes/__init__.py
impresso_commons/classes/contentitem.py
impresso_commons/data/config/GDL.json
impresso_commons/data/config/JDG.json
impresso_commons/data/config/cluster.json
impresso_commons/data/config/conf.json
impresso_commons/data/config/remaining_nps.json
impresso_commons/data/xmi/typesystem.xml
impresso_commons/images/__init__.py
impresso_commons/images/img_utils.py
impresso_commons/images/olive_boxes.py
impresso_commons/path/__init__.py
impresso_commons/path/path_fs.py
impresso_commons/path/path_s3.py
impresso_commons/text/__init__.py
impresso_commons/text/helpers.py
impresso_commons/text/rebuilder.py
impresso_commons/utils/__init__.py
impresso_commons/utils/config_loader.py
impresso_commons/utils/daskutils.py
impresso_commons/utils/kube.py
impresso_commons/utils/s3.py
impresso_commons/utils/s3_delete.py
impresso_commons/utils/uima.py
impresso_commons/utils/utils.py
impresso_pycommons.egg-info/PKG-INFO
impresso_pycommons.egg-info/SOURCES.txt
impresso_pycommons.egg-info/dependency_links.txt
impresso_pycommons.egg-info/entry_points.txt
impresso_pycommons.egg-info/requires.txt
impresso_pycommons.egg-info/top_level.txt