Metadata-Version: 2.1
Name: impresso-pycommons
Version: 0.12.8
Summary: UNKNOWN
Home-page: https://github.com/impresso/impresso-pycommons
Author: Matteo Romanello, Maud Ehrmann
Author-email: matteo.romanello@epfl.ch, maud.ehrmann@epfl.ch
License: UNKNOWN
Platform: UNKNOWN
Classifier: Programming Language :: Python :: 3
Classifier: Programming Language :: Python :: 3.6
Classifier: Programming Language :: Python :: 3.7
Requires-Python: >=3.6
